{
    "zero_optimization": {
        "stage": 3,
        "offload_optimizer": {
            "device": "none"
        },
        "offload_param": {
            "device": "none"
        },
        "overlap_comm": true,
        "contiguous_gradients": true,
        "sub_group_size": 1e9,
        "reduce_bucket_size": "auto",
        "stage3_prefetch_bucket_size": "auto",
        "stage3_param_persistence_threshold": "auto",
        "stage3_max_live_parameters": 1e9,
        "stage3_max_reuse_distance": 1e9,
        "stage3_gather_16bit_weights_on_model_save": true
    },
    "train_micro_batch_size_per_gpu": 4,
    "train_batch_size": 128,
    "gradient_accumulation_steps": 8,
    "zero_allow_untested_optimizer": true,
    "gradient_clipping": "auto",
    "fp16": {
        "enabled": true
    },
    "allgather_bucket_size": 5e8,
    "reduce_scatter": true,
    "wall_clock_breakdown": false,
    "distributed_world_size": 2,
    "activation_checkpointing": {
        "partition_activations": true,
        "contiguous_memory_optimization": true,
        "cpu_checkpointing": false
    }
}
